{"days_since_last_activity":[{"Period":"2016_09_10","days_since_last_activity":"IN last 7 Days","customers":278,"distribution":0.018291880510593498,"future_value":35.76},{"Period":"2016_09_10","days_since_last_activity":"IN Last 30 Days","customers":808,"distribution":0.053164890117120674,"future_value":82.44},{"Period":"2016_09_10","days_since_last_activity":"IN last 60 Days","customers":1038,"distribution":0.0682984603237268,"future_value":103.99},{"Period":"2016_09_10","days_since_last_activity":"IN Last 90 days","customers":951,"distribution":0.0625740228977497,"future_value":81},{"Period":"2016_09_10","days_since_last_activity":"> 90 Days","customers":12123,"distribution":0.7976707461508094,"future_value":249.67},{"Period":"2016_09_25","days_since_last_activity":"IN last 7 Days","customers":278,"distribution":0.018291880510593498,"future_value":35.76},{"Period":"2016_09_25","days_since_last_activity":"IN Last 30 Days","customers":808,"distribution":0.053164890117120674,"future_value":82.44},{"Period":"2016_09_25","days_since_last_activity":"IN last 60 Days","customers":1038,"distribution":0.0682984603237268,"future_value":103.99},{"Period":"2016_09_25","days_since_last_activity":"IN Last 90 days","customers":951,"distribution":0.0625740228977497,"future_value":81},{"Period":"2016_09_25","days_since_last_activity":"> 90 Days","customers":12123,"distribution":0.7976707461508094,"future_value":249.67}]}
